automate_ML/__init__.py
automate_ML/classification/__init__.py
automate_ML/classification/classification.py
automate_ML/dry_run/__init__.py
automate_ML/dry_run/dry_run.py
automate_ML/preprocessing/__init__.py
automate_ML/preprocessing/preprocessing.py
automate_ML/regression/__init__.py
automate_ML/regression/regression.py
automate_ML-1.0.31.dist-info/LICENSE
automate_ML-1.0.31.dist-info/METADATA
automate_ML-1.0.31.dist-info/WHEEL
automate_ML-1.0.31.dist-info/top_level.txt
automate_ML-1.0.31.dist-info/RECORD
